flaskservice/__init__.py
flaskservice/_base.py
tests/__init__.py
tests/test_app.py
flaskservice-0.0.4.dist-info/LICENSE
flaskservice-0.0.4.dist-info/METADATA
flaskservice-0.0.4.dist-info/WHEEL
flaskservice-0.0.4.dist-info/top_level.txt
flaskservice-0.0.4.dist-info/RECORD
