Metadata-Version: 2.1
Name: flaskservice
Version: 0.0.4
Summary: Quick start web services
Home-page: https://github.com/jlsneto/flaskservice
Author: Joab Leite
Author-email: jlsn1@ifal.edu.br
License: UNKNOWN
Platform: UNKNOWN
Classifier: Programming Language :: Python :: 3
Classifier: License :: OSI Approved :: MIT License
Classifier: Operating System :: OS Independent
Requires-Python: >=3.6
Requires-Dist: aniso8601 (==9.0.1)
Requires-Dist: cereja
Requires-Dist: certifi (==2020.12.5)
Requires-Dist: chardet (==4.0.0)
Requires-Dist: click (==8.0.1)
Requires-Dist: Flask
Requires-Dist: Flask-Cors
Requires-Dist: Flask-RESTful
Requires-Dist: idna (==3.2)
Requires-Dist: itsdangerous (==2.0.1)
Requires-Dist: Jinja2 (==3.0.1)
Requires-Dist: MarkupSafe (==2.0.1)
Requires-Dist: pytz (==2021.1)
Requires-Dist: requests
Requires-Dist: six (==1.16.0)
Requires-Dist: urllib3 (==1.26.5)
Requires-Dist: Werkzeug (==2.0.1)
